CHANGES.rst
CONTRIBUTORS.rst
LICENSE.GPL
LICENSE.rst
MANIFEST.in
README.rst
requirements.txt
setup.cfg
setup.py
docs/index.rst
src/collective/__init__.py
src/collective.contact.importexport.egg-info/PKG-INFO
src/collective.contact.importexport.egg-info/SOURCES.txt
src/collective.contact.importexport.egg-info/dependency_links.txt
src/collective.contact.importexport.egg-info/entry_points.txt
src/collective.contact.importexport.egg-info/namespace_packages.txt
src/collective.contact.importexport.egg-info/not-zip-safe
src/collective.contact.importexport.egg-info/requires.txt
src/collective.contact.importexport.egg-info/top_level.txt
src/collective/contact/__init__.py
src/collective/contact/importexport/__init__.py
src/collective/contact/importexport/configure.zcml
src/collective/contact/importexport/interfaces.py
src/collective/contact/importexport/setuphandlers.py
src/collective/contact/importexport/testing.py
src/collective/contact/importexport/testing.zcml
src/collective/contact/importexport/browser/__init__.py
src/collective/contact/importexport/browser/configure.zcml
src/collective/contact/importexport/browser/import_view.py
src/collective/contact/importexport/browser/overrides/.gitkeep
src/collective/contact/importexport/browser/static/.gitkeep
src/collective/contact/importexport/locales/collective.contact.importexport.pot
src/collective/contact/importexport/locales/update.sh
src/collective/contact/importexport/locales/en/LC_MESSAGES/collective.contact.importexport.po
src/collective/contact/importexport/locales/fr/LC_MESSAGES/collective.contact.importexport.po
src/collective/contact/importexport/profiles/default/browserlayer.xml
src/collective/contact/importexport/profiles/default/metadata.xml
src/collective/contact/importexport/profiles/default/registry.xml
src/collective/contact/importexport/profiles/default/types/directory.xml
src/collective/contact/importexport/profiles/uninstall/browserlayer.xml
src/collective/contact/importexport/tests/__init__.py
src/collective/contact/importexport/tests/test_import.py
src/collective/contact/importexport/tests/test_robot.py
src/collective/contact/importexport/tests/test_setup.py
src/collective/contact/importexport/tests/test_view.py
src/collective/contact/importexport/tests/data/functions.csv
src/collective/contact/importexport/tests/data/import_contacts.xls
src/collective/contact/importexport/tests/data/occupied_functions.csv
src/collective/contact/importexport/tests/data/organizations.csv
