Metadata-Version: 2.1
Name: collective.contact.importexport
Version: 0.3.9
Summary: An add-on for Plone for collective.contact suite
Home-page: https://pypi.python.org/pypi/collective.contact.importexport
Author: Benoit Suttor
Author-email: bsuttor@imio.be
License: GPL version 2
Keywords: Python Plone
Platform: UNKNOWN
Classifier: Environment :: Web Environment
Classifier: Framework :: Plone
Classifier: Framework :: Plone :: 4.3
Classifier: Programming Language :: Python
Classifier: Programming Language :: Python :: 2.7
Classifier: Operating System :: OS Independent
Classifier: License :: OSI Approved :: GNU General Public License v2 (GPLv2)
Provides-Extra: test
